[
    {
      "id":1,
      "urlImg": "/imgApp.png",
      "nameProject": "Project Alpha marias",
      "Top": 1,
      "Industry": "Technology",
      "Developer": true,
      "numberOfScores":4.1,
      "numberVotes": 120,
      "Category": ["Web Development", "Education", "AI"]
    },
    { "id":2,
      "urlImg": "/imgApp.png",
      "nameProject": "Project Beta",
      "Top": 10,
      "Industry": "Healthcare",
      "Developer": false,
      "numberOfScores": 4.5,
      "numberVotes": 110,
      "Category": ["Health Tech", "Innovation"]
    },
    { "id":3,
      "urlImg": "/imgApp.png",
      "nameProject": "Project Gamma",
      "Top": 15,
      "Industry": "Finance",
      "Developer": true,
      "numberOfScores": 3.5,
      "numberVotes": 95,
      "Category": ["FinTech", "Blockchain", "Security"]
    }
  ]
  